watch_run.cpython-312-darwin.so
watch_run-0.0.13.dist-info/METADATA
watch_run-0.0.13.dist-info/WHEEL
watch_run-0.0.13.dist-info/entry_points.txt
watch_run-0.0.13.dist-info/top_level.txt
watch_run-0.0.13.dist-info/RECORD
