Metadata-Version: 2.4
Name: watch_run
Version: 0.0.13
Summary: watch_run project
Author: Leo Lee
Author-email: liruihan500@sina.com
Requires-Dist: pillow>=10.0.0
Dynamic: author
Dynamic: author-email
Dynamic: description
Dynamic: description-content-type
Dynamic: requires-dist
Dynamic: summary
